aeoprs/core/models/__init__.py
aeoprs/core/models/mapper.py
aeoprs/core/models/model.py
aeoprsmodel-0.2.dist-info/METADATA
aeoprsmodel-0.2.dist-info/WHEEL
aeoprsmodel-0.2.dist-info/top_level.txt
aeoprsmodel-0.2.dist-info/RECORD
