Metadata-Version: 2.1
Name: aeoprsmodel
Version: 0.2
Summary: ARLAS Earth Observation Product Registration Service Model
Home-page: UNKNOWN
Author: Gisaïa
License: UNKNOWN
Platform: UNKNOWN
Requires-Python: >=3.11
